djocker/__init__.py
djocker/config.py
djocker/dockerize/__init__.py
djocker/dockerize/config.py
djocker/dockerize/handlers/__init__.py
djocker/dockerize/handlers/base.py
djocker/dockerize/handlers/compose.py
djocker/dockerize/handlers/entrypoint.py
djocker/dockerize/handlers/ubuntu.py
djocker/dockerize/templates/__init__.py
djocker/dockerize/utils/__init__.py
djocker/dockerize/utils/constants.py
djocker/utils/__init__.py
djocker/utils/ask.py
djocker/utils/cli.py
djocker/utils/colors.py
djocker/utils/docker_index.py
djocker/utils/file.py
djocker-0.2.1.dist-info/LICENSE.txt
djocker-0.2.1.dist-info/METADATA
djocker-0.2.1.dist-info/RECORD
djocker-0.2.1.dist-info/WHEEL
djocker-0.2.1.dist-info/entry_points.txt
djocker-0.2.1.dist-info/top_level.txt
